avocentdpdu/__init__.py
avocentdpdu/avocentdpdu.py
avocentdpdu-2.0.1.dist-info/LICENSE
avocentdpdu-2.0.1.dist-info/METADATA
avocentdpdu-2.0.1.dist-info/WHEEL
avocentdpdu-2.0.1.dist-info/top_level.txt
avocentdpdu-2.0.1.dist-info/RECORD
