Metadata-Version: 2.1
Name: avocentdpdu
Version: 2.0.1
Summary: Library to control Avocent DPDU10x PDUs
Author-email: William Gibson <william.gibson.wg@gmail.com>
Project-URL: Homepage, https://github.com/wgprojects/avocent_pdu
Project-URL: Issues, https://github.com/wgprojects/avocent_pdu/issues
Classifier: Programming Language :: Python :: 3
Classifier: License :: OSI Approved :: MIT License
Classifier: Operating System :: OS Independent
Requires-Python: >=3.8
License-File: LICENSE
